{
  "type": "minecraft:crafting_shaped",
  "category": "misc",
  "key": {
    "E": {
      "item": "enchantcraft:enchanted_diamond"
    },
    "R": {
      "item": "minecraft:redstone_block"
    },
    "D": {
      "item": "minecraft:diamond"
    },
    "B": {
      "item": "minecraft:book"
    }
  },
  "pattern": [
    "RDR",
    "RBR",
    "RER"
  ],

  "result": {
    "count": 1,
    "id": "minecraft:enchanted_book",
    "components": {
      "minecraft:stored_enchantments": {
        "levels": {
          "minecraft:efficiency": 1
        }
      }
    }
  }
}
